[ {
  "sentence_tokens" : [ "In", "this", "report", ",", "we", "describe", "a", "case", "of", "a", "42", "year", "old", "woman", "diagnosed", "during", "acute", "infection", "who", "rapidly", "and", "permanently", "suppressed", "her", "viremia", "in", "the", "absence", "of", "antiretroviral", "therapy", "(", "ART", ")", "." ],
  "event_indices" : [ 22, 23, 24, 25, 26, 27, 28, 29, 30, 31, 32, 33 ],
  "type" : "Negative_activation",
  "polarity" : false,
  "controller_indices" : [ 32, 33 ],
  "controlled_indices" : [ 24, 25 ],
  "trigger_indices" : [ 22, 23 ]
}, {
  "sentence_tokens" : [ "In", "this", "report", ",", "we", "describe", "a", "case", "of", "a", "42", "year", "old", "woman", "diagnosed", "during", "acute", "infection", "who", "rapidly", "and", "permanently", "suppressed", "her", "viremia", "in", "the", "absence", "of", "antiretroviral", "therapy", "(", "ART", ")", "." ],
  "event_indices" : [ 17, 18, 19, 20, 21, 22, 23, 24, 25 ],
  "type" : "Negative_activation",
  "polarity" : false,
  "controller_indices" : [ 17, 18 ],
  "controlled_indices" : [ 24, 25 ],
  "trigger_indices" : [ 22, 23 ]
}, {
  "sentence_tokens" : [ "Elite", "controllers", "(", "EC", ")", ",", "a", "small", "subset", "of", "the", "HIV", "positive", "population", "(", "<", "1", "%", ")", ",", "suppress", "HIV", "viremia", "below", "the", "limit", "of", "quantification", "of", "clinical", "viral", "load", "assays", "in", "the", "absence", "of", "antiretroviral", "therapy", "(", "ART", ")", "." ],
  "event_indices" : [ 3, 4, 5, 6, 7, 8, 9, 10, 11, 12, 13, 14, 15, 16, 17, 18, 19, 20, 21, 22, 23 ],
  "type" : "Negative_activation",
  "polarity" : false,
  "controller_indices" : [ 3, 4 ],
  "controlled_indices" : [ 22, 23 ],
  "trigger_indices" : [ 20, 21 ]
} ]